youtube_to_docs/__init__.py
youtube_to_docs/infographic.py
youtube_to_docs/llms.py
youtube_to_docs/main.py
youtube_to_docs/mcp_server.py
youtube_to_docs/models.py
youtube_to_docs/prices.py
youtube_to_docs/storage.py
youtube_to_docs/transcript.py
youtube_to_docs/tts.py
youtube_to_docs/utils.py
youtube_to_docs/video.py
youtube_to_docs-0.0.63.dist-info/licenses/LICENSE
youtube_to_docs-0.0.63.dist-info/METADATA
youtube_to_docs-0.0.63.dist-info/WHEEL
youtube_to_docs-0.0.63.dist-info/entry_points.txt
youtube_to_docs-0.0.63.dist-info/top_level.txt
youtube_to_docs-0.0.63.dist-info/RECORD
