Metadata-Version: 2.4
Name: youtube-to-docs
Version: 0.0.63
Summary: Convert YouTube videos into structured docs, summaries, audio, and visual assets for easier discovery
Requires-Python: >=3.12
License-File: LICENSE
Requires-Dist: google-api-python-client>=2.187.0
Requires-Dist: isodate>=0.7.2
Requires-Dist: mcp>=1.26.0
Requires-Dist: polars>=1.36.1
Requires-Dist: requests>=2.32.5
Requires-Dist: rich>=14.2.0
Requires-Dist: rich-argparse>=1.7.2
Requires-Dist: youtube-transcript-api>=1.2.3
Provides-Extra: aws
Provides-Extra: azure
Requires-Dist: openai>=1.56.0; extra == "azure"
Provides-Extra: gcp
Requires-Dist: google-genai; extra == "gcp"
Requires-Dist: google-cloud-speech>=2.29.0; extra == "gcp"
Requires-Dist: google-cloud-storage; extra == "gcp"
Requires-Dist: google-cloud-texttospeech; extra == "gcp"
Provides-Extra: workspace
Requires-Dist: google-auth-oauthlib; extra == "workspace"
Requires-Dist: pypandoc>=1.16.2; extra == "workspace"
Requires-Dist: pypandoc_binary>=1.16.2; extra == "workspace"
Provides-Extra: m365
Requires-Dist: msal>=1.34.0; extra == "m365"
Requires-Dist: fastexcel>=0.12.0; extra == "m365"
Requires-Dist: xlsxwriter>=3.2.9; extra == "m365"
Requires-Dist: pypandoc>=1.16.2; extra == "m365"
Requires-Dist: pypandoc_binary>=1.16.2; extra == "m365"
Provides-Extra: audio
Requires-Dist: yt-dlp>=2026.01.29; extra == "audio"
Provides-Extra: video
Requires-Dist: static-ffmpeg>=2.13; extra == "video"
Provides-Extra: all
Requires-Dist: youtube-to-docs[audio,aws,azure,gcp,m365,video,workspace]; extra == "all"
Dynamic: license-file
